openmeeg-2.5.15.dist-info/RECORD
openmeeg-2.5.15.dist-info/WHEEL
openmeeg-2.5.15.dist-info/top_level.txt
openmeeg-2.5.15.dist-info/METADATA
openmeeg/numpy.i
openmeeg/_openmeeg.i
openmeeg/_make_geometry.py
openmeeg/_openmeeg.abi3.so
openmeeg/__init__.py
openmeeg/_distributor_init.py
openmeeg/_openmeeg_wrap.cpp
openmeeg/_openmeeg_wrapper.py
openmeeg/_utils.py
openmeeg/tests/test_sensors.py
openmeeg/tests/conftest.py
openmeeg/tests/test_python.py
openmeeg/tests/test_mesh.py
openmeeg/tests/__init__.py
openmeeg/tests/test_symmatrix.py
openmeeg/tests/test_matrix.py
openmeeg/tests/test_vector.py
openmeeg/tests/test_geometry.py
openmeeg/tests/test_doc.py
openmeeg/.dylibs/libOpenMEEG.1.1.0.dylib
openmeeg/.dylibs/libgfortran.5.dylib
openmeeg/.dylibs/libOpenMEEGMaths.1.1.0.dylib
openmeeg/.dylibs/libgcc_s.2.dylib
openmeeg/.dylibs/libopenblas.0.dylib
