Metadata-Version: 2.1
Name: openmeeg
Version: 2.5.15
Summary: Forward problems solver in the field of EEG and MEG.
Maintainer-email: Alexandre Gramfort <alexandre.gramfort@inria.fr>
License: CECILL-B
Project-URL: Homepage, http://openmeeg.github.io
Project-URL: Download, http://github.com/openmeeg/openmeeg
Project-URL: Bug Tracker, https://github.com/openmeeg/openmeeg/issues
Project-URL: Documentation, https://openmeeg.github.io
Project-URL: Source code, https://github.com/openmeeg/openmeeg
Keywords: neuroscience,neuroimaging,MEG,EEG,ECoG,sEEG,iEEG,brain
Classifier: Intended Audience :: Science/Research
Classifier: Intended Audience :: Developers
Classifier: License :: OSI Approved
Classifier: Programming Language :: Python
Classifier: Topic :: Software Development
Classifier: Topic :: Scientific/Engineering
Classifier: Operating System :: Microsoft :: Windows
Classifier: Operating System :: POSIX
Classifier: Operating System :: Unix
Classifier: Operating System :: MacOS
Classifier: Programming Language :: Python :: 3
Requires-Python: >=3.10
Requires-Dist: numpy
